{
  "name": "Jayden Jensen",
  "age": 42,
  "address": {
    "street": "Nebe Park",
    "city": "Ajhutuwi",
    "state": "SC",
    "zip": "96596"
  },
  "contact": {
    "phone": "(878) 981-5624",
    "servicePhone": "800152742"
  },
  "birthday": "1998-07-10T16:47:56.040Z",
  "ip": "43.201.142.110",
  "foo": "bar",
  "profile": {
    "about": "Puc sosirfu nuhago zo hebhec felobdog zeumpo bev cuve iwejulo tu zoreko piw fu agfieju. Gu eveme sev unnoh web kocki akvo fudegi gigoha lub wamohu pabaj. Difew ennuven ibri tesuk ol owa bues gewudfan giz piram faase ru ekekik gu. Ettok ka uh gudcinov tu ucejinu welaclap zuhuf lug egozor od daozubot zi zizewto urit. Bidnenpuw se tidtom jofaspiv mejsipuk gueggaw sudbu umigi si usece beipabu nomli ludaki te wopzowrov.",
    "bio": "Gej hesju fab hibkuh godi lisezojo famuhwus tezvadaf hoolunu marho pu zilhihwa nah fo acadi uwejo. Gugbulhod cof wezvah leva siw ajihe hubughod kavel nutah pujeneh wihbepo begzib urvih. Zujiv tudteduz uruginek kuipo pegcil dupetur ef tetgezro ezo nivu nukog fi dekjek lozhepih folmij hu cej."
  },
  "apiKey": "acac0fd690c473140c55fbde14f0ad553b1ab0f848fe31512d14a748498ad379",
  "currency": {
    "code": "TWD",
    "name": "Taiwan New Dollar"
  }
}